{"is_source_file": false, "format": "", "description": "", "external_files": [], "external_methods": [], "published": [], "classes": [], "methods": [], "calls": [], "search-terms": [], "state": 2, "file_id": 20, "knowledge_revision": 52, "git_revision": "6d4bbdec51704441698cb2ccfd96772954a8a822", "hash": "a6d660835acf87fa1ea14593ef746aac", "format-version": 4, "code-base-name": "weather_frontend", "filename": "weather_frontend/package.json", "revision_history": [{"52": "6d4bbdec51704441698cb2ccfd96772954a8a822"}]}